{"cameraMode":{"drawMode":0,"name":"Shaded","section":"Shading Mode"},"sceneLighting":true,"audioPlay":false,"sceneViewState":{"m_AlwaysRefresh":false,"showFog":true,"showSkybox":true,"showFlares":true,"showImageEffects":true,"showParticleSystems":true,"showVisualEffectGraphs":true,"m_FxEnabled":true},"in2DMode":false,"pivot":{"x":0.9196324348449707,"y":8.205679893493653,"z":-2.7180070877075197},"rotation":{"x":-0.39207008481025698,"y":-0.2771243751049042,"z":0.12524135410785676,"w":-0.8682103753089905},"size":1.0622589588165284,"orthographic":false}